bina/__init__.py
bina/cli.py
bina/core/__init__.py
bina/core/baseline.py
bina/core/config.py
bina/core/engine.py
bina/core/loader.py
bina/core/models.py
bina/core/registry.py
bina/integrations/github_reporter.py
bina/integrations/sarif_reporter.py
bina/python/__init__.py
bina/python/parser.py
bina/python/rules/__init__.py
bina/python/rules/best_practices.py
bina/python/rules/logic.py
bina/python/rules/naming.py
bina/reporters/__init__.py
bina_review-0.3.4.dist-info/METADATA
bina_review-0.3.4.dist-info/WHEEL
bina_review-0.3.4.dist-info/entry_points.txt
bina_review-0.3.4.dist-info/licenses/LICENSE
bina_review-0.3.4.dist-info/RECORD
