Metadata-Version: 2.4
Name: bina-review
Version: 0.3.4
Summary: Deterministic, rule-based static analysis tool for Python.
License-File: LICENSE
Author: Bina Team
Requires-Python: >=3.9,<4.0
Classifier: Programming Language :: Python :: 3
Classifier: Programming Language :: Python :: 3.9
Classifier: Programming Language :: Python :: 3.10
Classifier: Programming Language :: Python :: 3.11
Classifier: Programming Language :: Python :: 3.12
Classifier: Programming Language :: Python :: 3.13
Classifier: Programming Language :: Python :: 3.14
Requires-Dist: PyYAML (>=6.0,<7.0)
Requires-Dist: click (>=8.1,<9.0)
Requires-Dist: requests (>=2.31,<3.0)
Requires-Dist: rich (>=13.0,<14.0)
Project-URL: Homepage, https://github.com/Bonyad-Labs/bina-review
Project-URL: Repository, https://github.com/Bonyad-Labs/bina-review
